cli.py
chat_client/__init__.py
chat_client/client.py
terminal_chat_room-1.0.2.dist-info/METADATA
terminal_chat_room-1.0.2.dist-info/WHEEL
terminal_chat_room-1.0.2.dist-info/entry_points.txt
terminal_chat_room-1.0.2.dist-info/top_level.txt
terminal_chat_room-1.0.2.dist-info/RECORD
